LICENSE
MANIFEST.in
README.md
requirements.txt
setup.cfg
setup.py
iempy/__init__.py
iempy/iempy.py
iempy.egg-info/PKG-INFO
iempy.egg-info/SOURCES.txt
iempy.egg-info/dependency_links.txt
iempy.egg-info/not-zip-safe
iempy.egg-info/top_level.txt