Metadata-Version: 2.1
Name: iempy
Version: 0.0.1
Summary: Practice Python Package
Home-page: https://github.com/statenandrea33/iempy
Author: Andrea Staten
Author-email: statenandrea33@gmail.com
License: MIT license
Keywords: iempy
Classifier: Development Status :: 2 - Pre-Alpha
Classifier: Intended Audience :: Developers
Classifier: License :: OSI Approved :: MIT License
Classifier: Natural Language :: English
Classifier: Programming Language :: Python :: 3
Classifier: Programming Language :: Python :: 3.7
Classifier: Programming Language :: Python :: 3.8
Classifier: Programming Language :: Python :: 3.9
Classifier: Programming Language :: Python :: 3.10
Requires-Python: >=3.7
License-File: LICENSE
